azure/mgmt/elasticsan/__init__.py
azure/mgmt/elasticsan/_configuration.py
azure/mgmt/elasticsan/_elastic_san_mgmt_client.py
azure/mgmt/elasticsan/_patch.py
azure/mgmt/elasticsan/_serialization.py
azure/mgmt/elasticsan/_version.py
azure/mgmt/elasticsan/py.typed
azure/mgmt/elasticsan/aio/__init__.py
azure/mgmt/elasticsan/aio/_configuration.py
azure/mgmt/elasticsan/aio/_elastic_san_mgmt_client.py
azure/mgmt/elasticsan/aio/_patch.py
azure/mgmt/elasticsan/aio/operations/__init__.py
azure/mgmt/elasticsan/aio/operations/_elastic_sans_operations.py
azure/mgmt/elasticsan/aio/operations/_operations.py
azure/mgmt/elasticsan/aio/operations/_patch.py
azure/mgmt/elasticsan/aio/operations/_private_endpoint_connections_operations.py
azure/mgmt/elasticsan/aio/operations/_private_link_resources_operations.py
azure/mgmt/elasticsan/aio/operations/_skus_operations.py
azure/mgmt/elasticsan/aio/operations/_volume_groups_operations.py
azure/mgmt/elasticsan/aio/operations/_volume_snapshots_operations.py
azure/mgmt/elasticsan/aio/operations/_volumes_operations.py
azure/mgmt/elasticsan/models/__init__.py
azure/mgmt/elasticsan/models/_elastic_san_mgmt_client_enums.py
azure/mgmt/elasticsan/models/_models_py3.py
azure/mgmt/elasticsan/models/_patch.py
azure/mgmt/elasticsan/operations/__init__.py
azure/mgmt/elasticsan/operations/_elastic_sans_operations.py
azure/mgmt/elasticsan/operations/_operations.py
azure/mgmt/elasticsan/operations/_patch.py
azure/mgmt/elasticsan/operations/_private_endpoint_connections_operations.py
azure/mgmt/elasticsan/operations/_private_link_resources_operations.py
azure/mgmt/elasticsan/operations/_skus_operations.py
azure/mgmt/elasticsan/operations/_volume_groups_operations.py
azure/mgmt/elasticsan/operations/_volume_snapshots_operations.py
azure/mgmt/elasticsan/operations/_volumes_operations.py
azure_mgmt_elasticsan-1.1.0.dist-info/LICENSE
azure_mgmt_elasticsan-1.1.0.dist-info/METADATA
azure_mgmt_elasticsan-1.1.0.dist-info/WHEEL
azure_mgmt_elasticsan-1.1.0.dist-info/top_level.txt
azure_mgmt_elasticsan-1.1.0.dist-info/RECORD
